xp_extinction_toolkit/BOSZ_spectra.npy
xp_extinction_toolkit/ExtinctionToolkit.py
xp_extinction_toolkit/XP_extinction_curve.csv
xp_extinction_toolkit/__init__.py
xp_extinction_toolkit/usage_guide.py
xp_extinction_toolkit/filters/2MASS_2MASS.H.dat
xp_extinction_toolkit/filters/2MASS_2MASS.J.dat
xp_extinction_toolkit/filters/2MASS_2MASS.Ks.dat
xp_extinction_toolkit/filters/GAIA_GAIA3.G.dat
xp_extinction_toolkit/filters/GAIA_GAIA3.Gbp.dat
xp_extinction_toolkit/filters/GAIA_GAIA3.Grp.dat
xp_extinction_toolkit/filters/GALEX_GALEX.FUV.dat
xp_extinction_toolkit/filters/GALEX_GALEX.NUV.dat
xp_extinction_toolkit/filters/GCPD_Johnson.B.dat
xp_extinction_toolkit/filters/GCPD_Johnson.R.dat
xp_extinction_toolkit/filters/GCPD_Johnson.U.dat
xp_extinction_toolkit/filters/GCPD_Johnson.V.dat
xp_extinction_toolkit/filters/PAN-STARRS_PS1.g.dat
xp_extinction_toolkit/filters/PAN-STARRS_PS1.i.dat
xp_extinction_toolkit/filters/PAN-STARRS_PS1.r.dat
xp_extinction_toolkit/filters/PAN-STARRS_PS1.y.dat
xp_extinction_toolkit/filters/PAN-STARRS_PS1.z.dat
xp_extinction_toolkit/filters/SLOAN_SDSS.g.dat
xp_extinction_toolkit/filters/SLOAN_SDSS.i.dat
xp_extinction_toolkit/filters/SLOAN_SDSS.r.dat
xp_extinction_toolkit/filters/SLOAN_SDSS.u.dat
xp_extinction_toolkit/filters/SLOAN_SDSS.z.dat
xp_extinction_toolkit/filters/WISE_WISE.W1.dat
xp_extinction_toolkit/filters/WISE_WISE.W2.dat
xp_extinction_toolkit/filters/WISE_WISE.W3.dat
xp_extinction_toolkit/filters/WISE_WISE.W4.dat
XP_Extinction_Toolkit-1.0.dist-info/LICENSE.rtf
XP_Extinction_Toolkit-1.0.dist-info/METADATA
XP_Extinction_Toolkit-1.0.dist-info/WHEEL
XP_Extinction_Toolkit-1.0.dist-info/entry_points.txt
XP_Extinction_Toolkit-1.0.dist-info/top_level.txt
XP_Extinction_Toolkit-1.0.dist-info/RECORD
