Metadata-Version: 2.1
Name: XP-Extinction-Toolkit
Version: 1.0
Summary: Extinction correction package using extinction curves derived from XP spectra
Home-page: https://github.com/vnohhf/XP_Extinction_Toolkit
Author: Ruoyi Zhang
Author-email: zry@mail.bnu.edu.cn
Classifier: Development Status :: 4 - Beta
Classifier: Intended Audience :: Science/Research
Classifier: Programming Language :: Python :: 3
Classifier: Programming Language :: Python :: 3.7
License-File: LICENSE.rtf
Requires-Dist: numpy
Requires-Dist: pandas
Requires-Dist: tqdm
Requires-Dist: astropy
Requires-Dist: scipy
